core/__init__.py
core/engine.py
core/advanced/__init__.py
core/advanced/bias.py
core/advanced/toxicity.py
themis/__init__.py
themis/analytics/__init__.py
themis/cli/__init__.py
themis/cli/main.py
themis/core/__init__.py
themis/core/engine.py
themis/core/advanced/__init__.py
themis/core/advanced/bias.py
themis/core/advanced/toxicity.py
themis/core/differential_privacy/__init__.py
themis/core/differential_privacy/mechanisms.py
themis/core/evaluators/__init__.py
themis/core/evaluators/base.py
themis/core/evaluators/hallucination.py
themis/core/evaluators/semantic.py
themis/integrations/__init__.py
themis/testing/__init__.py
themis/testing/framework.py
themis/utils/__init__.py
themis_ai_eval-2.0.dist-info/licenses/LICENSE
themis_ai_eval-2.0.dist-info/METADATA
themis_ai_eval-2.0.dist-info/WHEEL
themis_ai_eval-2.0.dist-info/entry_points.txt
themis_ai_eval-2.0.dist-info/top_level.txt
themis_ai_eval-2.0.dist-info/RECORD
