Metadata-Version: 2.4
Name: themis-ai-eval
Version: 2.0
Summary: Comprehensive AI System Evaluation & Testing Framework
Home-page: https://github.com/themis-ai/themis
Author: Themis Team
Author-email: contact@themis-ai.dev
License: MIT
Project-URL: Documentation, https://themis-ai.readthedocs.io/
Project-URL: Source, https://github.com/themis-ai/themis
Project-URL: Tracker, https://github.com/themis-ai/themis/issues
Keywords: ai,ml,evaluation,testing,llm,bias,differential-privacy
Classifier: Development Status :: 4 - Beta
Classifier: Intended Audience :: Developers
Classifier: Intended Audience :: Science/Research
Classifier: License :: OSI Approved :: MIT License
Classifier: Operating System :: OS Independent
Classifier: Programming Language :: Python :: 3
Classifier: Programming Language :: Python :: 3.8
Classifier: Programming Language :: Python :: 3.9
Classifier: Programming Language :: Python :: 3.10
Classifier: Programming Language :: Python :: 3.11
Classifier: Topic :: Scientific/Engineering :: Artificial Intelligence
Classifier: Topic :: Software Development :: Libraries :: Python Modules
Classifier: Topic :: Software Development :: Testing
Requires-Python: >=3.8
License-File: LICENSE
Requires-Dist: numpy>=1.21.0
Requires-Dist: pandas>=1.3.0
Requires-Dist: scikit-learn>=1.0.0
Requires-Dist: torch>=1.9.0
Requires-Dist: transformers>=4.12.0
Requires-Dist: datasets>=1.16.0
Requires-Dist: nltk>=3.6
Requires-Dist: spacy>=3.4.0
Requires-Dist: sentence-transformers>=2.2.0
Requires-Dist: openai>=0.27.0
Requires-Dist: fastapi>=0.75.0
Requires-Dist: uvicorn>=0.17.0
Requires-Dist: mlflow>=1.20.0
Requires-Dist: requests>=2.25.0
Requires-Dist: tqdm>=4.62.0
Requires-Dist: plotly>=5.0.0
Requires-Dist: matplotlib>=3.4.0
Requires-Dist: seaborn>=0.11.0
Requires-Dist: pyyaml>=6.0
Requires-Dist: click>=8.0.0
Requires-Dist: jinja2>=3.0.0
Requires-Dist: jsonschema>=4.0.0
Requires-Dist: scipy>=1.7.0
Requires-Dist: networkx>=2.6.0
Requires-Dist: python-dotenv>=0.19.0
Provides-Extra: dev
Requires-Dist: pytest>=6.2.0; extra == "dev"
Requires-Dist: pytest-cov>=3.0.0; extra == "dev"
Requires-Dist: black>=22.0.0; extra == "dev"
Requires-Dist: flake8>=4.0.0; extra == "dev"
Requires-Dist: isort>=5.10.0; extra == "dev"
Requires-Dist: mypy>=0.910; extra == "dev"
Requires-Dist: pre-commit>=2.15.0; extra == "dev"
Provides-Extra: docs
Requires-Dist: sphinx>=4.0.0; extra == "docs"
Requires-Dist: sphinx-rtd-theme>=1.0.0; extra == "docs"
Requires-Dist: sphinx-autodoc-typehints>=1.12.0; extra == "docs"
Provides-Extra: full
Requires-Dist: tensorboard>=2.7.0; extra == "full"
Requires-Dist: wandb>=0.12.0; extra == "full"
Requires-Dist: ray>=1.9.0; extra == "full"
Provides-Extra: all
Requires-Dist: pytest>=6.2.0; extra == "all"
Requires-Dist: pytest-cov>=3.0.0; extra == "all"
Requires-Dist: black>=22.0.0; extra == "all"
Requires-Dist: flake8>=4.0.0; extra == "all"
Requires-Dist: isort>=5.10.0; extra == "all"
Requires-Dist: mypy>=0.910; extra == "all"
Requires-Dist: pre-commit>=2.15.0; extra == "all"
Requires-Dist: sphinx>=4.0.0; extra == "all"
Requires-Dist: sphinx-rtd-theme>=1.0.0; extra == "all"
Requires-Dist: sphinx-autodoc-typehints>=1.12.0; extra == "all"
Requires-Dist: tensorboard>=2.7.0; extra == "all"
Requires-Dist: wandb>=0.12.0; extra == "all"
Requires-Dist: ray>=1.9.0; extra == "all"
Dynamic: author
Dynamic: author-email
Dynamic: classifier
Dynamic: description
Dynamic: description-content-type
Dynamic: home-page
Dynamic: keywords
Dynamic: license
Dynamic: license-file
Dynamic: project-url
Dynamic: provides-extra
Dynamic: requires-dist
Dynamic: requires-python
Dynamic: summary
